nifwrapper/__init__.py
nifwrapper/nifAnnotation.py
nifwrapper/nifBenchmark.py
nifwrapper/nifDocument.py
nifwrapper/nifParser.py
nifwrapper/nifSentence.py
nifwrapper/nifUtils.py
nifwrapper/nifWrapper.py
nifwrapper-1.6.3.dist-info/LICENSE
nifwrapper-1.6.3.dist-info/METADATA
nifwrapper-1.6.3.dist-info/WHEEL
nifwrapper-1.6.3.dist-info/top_level.txt
nifwrapper-1.6.3.dist-info/RECORD
