Metadata-Version: 2.1
Name: nifwrapper
Version: 1.6.3
Summary: Parsing and storing NIF information
Home-page: https://github.com/henryrosalesmendez/nifwrapper
Author: Henry Rosales
Author-email: hrosmendez@gmail.com
License: UNKNOWN
Project-URL: Bug Reports, https://github.com/henryrosalesmendez/nifwrapper/issues
Project-URL: Funding, https://github.com/henryrosalesmendez/nifwrapper
Project-URL: Say Thanks!, https://github.com/henryrosalesmendez/nifwrapper
Project-URL: Source, https://github.com/henryrosalesmendez/nifwrapper
Keywords: NIF parser NLP
Platform: UNKNOWN
Classifier: Development Status :: 4 - Beta
Classifier: Intended Audience :: Education
Classifier: Topic :: Software Development :: Build Tools
Classifier: License :: OSI Approved :: GNU General Public License v3 (GPLv3)
Classifier: Programming Language :: Python :: 3
Classifier: Programming Language :: Python :: 3.4
Classifier: Programming Language :: Python :: 3.5
Classifier: Programming Language :: Python :: 3.6
Classifier: Programming Language :: Python :: 3.7
Classifier: Programming Language :: Python :: 3.8
Requires-Python: >=3, <4
Provides-Extra: dev
Requires-Dist: check-manifest ; extra == 'dev'
Provides-Extra: test
Requires-Dist: coverage ; extra == 'test'
